odoo/addons/delivery_carrier_manual_price/README.rst
odoo/addons/delivery_carrier_manual_price/__init__.py
odoo/addons/delivery_carrier_manual_price/__manifest__.py
odoo/addons/delivery_carrier_manual_price/i18n/delivery_carrier_manual_price.pot
odoo/addons/delivery_carrier_manual_price/i18n/it.po
odoo/addons/delivery_carrier_manual_price/models/__init__.py
odoo/addons/delivery_carrier_manual_price/models/delivery_carrier.py
odoo/addons/delivery_carrier_manual_price/models/sale_order.py
odoo/addons/delivery_carrier_manual_price/readme/CONTRIBUTORS.md
odoo/addons/delivery_carrier_manual_price/readme/DESCRIPTION.md
odoo/addons/delivery_carrier_manual_price/readme/USAGE.md
odoo/addons/delivery_carrier_manual_price/static/description/icon.png
odoo/addons/delivery_carrier_manual_price/static/description/index.html
odoo/addons/delivery_carrier_manual_price/tests/__init__.py
odoo/addons/delivery_carrier_manual_price/tests/test_delivery_carrier_manual_price.py
odoo/addons/delivery_carrier_manual_price/views/delivery_view.xml
odoo/addons/delivery_carrier_manual_price/wizard/__init__.py
odoo/addons/delivery_carrier_manual_price/wizard/choose_delivery_carrier.py
odoo/addons/delivery_carrier_manual_price/wizard/choose_delivery_carrier_views.xml
odoo_addon_delivery_carrier_manual_price-18.0.1.0.0.2.dist-info/METADATA
odoo_addon_delivery_carrier_manual_price-18.0.1.0.0.2.dist-info/WHEEL
odoo_addon_delivery_carrier_manual_price-18.0.1.0.0.2.dist-info/top_level.txt
odoo_addon_delivery_carrier_manual_price-18.0.1.0.0.2.dist-info/RECORD
